adelie/constraint.py
adelie/matrix.py
adelie/glm.py
adelie/configs.py
adelie/solver.py
adelie/io.py
adelie/optimization.py
adelie/__init__.py
adelie/logger.py
adelie/adelie_core.cpython-39-darwin.so
adelie/diagnostic.py
adelie/cv.py
adelie/sklearn.py
adelie/bcd.py
adelie/data.py
adelie/state.py
adelie/.dylibs/libomp.dylib
adelie/src/py_constraint.cpp
adelie/src/py_optimization.cpp
adelie/src/py_glm.cpp
adelie/src/py_bcd.cpp
adelie/src/py_decl.hpp
adelie/src/py_matrix_utils.cpp
adelie/src/py_configs.cpp
adelie/src/py_state.cpp
adelie/src/py_adelie_core.cpp
adelie/src/py_matrix.cpp
adelie/src/py_sklearn.cpp
adelie/src/py_matrix_utils_blas.cpp
adelie/src/py_io.cpp
adelie/src/py_solver.cpp
adelie/src/include/adelie_core/configs.hpp
adelie/src/include/adelie_core/util/tqdm.hpp
adelie/src/include/adelie_core/util/stopwatch.hpp
adelie/src/include/adelie_core/util/macros.hpp
adelie/src/include/adelie_core/util/omp.hpp
adelie/src/include/adelie_core/util/algorithm.hpp
adelie/src/include/adelie_core/util/queue.hpp
adelie/src/include/adelie_core/util/functional.hpp
adelie/src/include/adelie_core/util/counting_iterator.hpp
adelie/src/include/adelie_core/util/exceptions.hpp
adelie/src/include/adelie_core/util/types.hpp
adelie/src/include/adelie_core/util/format.hpp
adelie/src/include/adelie_core/util/eigen/map_sparsevector.hpp
adelie/src/include/adelie_core/optimization/bisect.hpp
adelie/src/include/adelie_core/optimization/symmetric_penalty.hpp
adelie/src/include/adelie_core/optimization/pinball.hpp
adelie/src/include/adelie_core/optimization/nnls.hpp
adelie/src/include/adelie_core/optimization/lasso_full.hpp
adelie/src/include/adelie_core/optimization/pinball_full.hpp
adelie/src/include/adelie_core/optimization/linqp_full.hpp
adelie/src/include/adelie_core/optimization/newton.hpp
adelie/src/include/adelie_core/optimization/nnqp_full.hpp
adelie/src/include/adelie_core/optimization/search_pivot.hpp
adelie-1.1.52.dist-info/RECORD
adelie-1.1.52.dist-info/LICENSE
adelie-1.1.52.dist-info/WHEEL
adelie-1.1.52.dist-info/top_level.txt
adelie-1.1.52.dist-info/METADATA
