Metadata-Version: 2.2
Name: adelie
Version: 1.1.52
Summary: A fast, flexible package for group elastic net.
Author: James Yang
Author-email: James Yang <jamesyang916@gmail.com>
Maintainer: James Yang
Maintainer-email: James Yang <jamesyang916@gmail.com>
License: MIT License
Project-URL: Homepage, https://github.com/JamesYang007/adelie
Project-URL: Documentation, https://jamesyang007.github.io/adelie
Project-URL: Repository, https://github.com/JamesYang007/adelie
Keywords: group lasso,group elastic net,lasso,elastic net
Classifier: Intended Audience :: Science/Research
Classifier: Intended Audience :: Developers
Classifier: Programming Language :: Python
Classifier: Programming Language :: Python :: 3
Classifier: Programming Language :: Python :: 3.9
Classifier: Programming Language :: Python :: 3.10
Classifier: Programming Language :: Python :: 3.11
Classifier: Programming Language :: Python :: 3.12
Classifier: Programming Language :: Python :: 3 :: Only
Classifier: License :: OSI Approved :: MIT License
Classifier: Topic :: Software Development
Classifier: Topic :: Scientific/Engineering
Classifier: Typing :: Typed
Classifier: Operating System :: OS Independent
Requires-Python: >=3.9
License-File: LICENSE
Requires-Dist: numpy<2,>=1.24.2
Requires-Dist: scipy<2,>=1.10.1
Requires-Dist: matplotlib<4,>=3.7.0
Requires-Dist: ipython<9,>=8.17.2
Requires-Dist: scikit-learn<2,>=1.3.2
Dynamic: author
Dynamic: maintainer
